py_hrmc/__init__.py
py_hrmc/box.py
py_hrmc/graphs.py
py_hrmc/hrmc.py
py_hrmc/log.py
py_hrmc/move.py
py_hrmc/total_scattering.py
py_hrmc/utils.py
py_hrmc/vector.py
py_hrmc_sim-0.1.0.dist-info/LICENSE
py_hrmc_sim-0.1.0.dist-info/METADATA
py_hrmc_sim-0.1.0.dist-info/WHEEL
py_hrmc_sim-0.1.0.dist-info/top_level.txt
py_hrmc_sim-0.1.0.dist-info/RECORD
