Metadata-Version: 2.1
Name: py-hrmc-sim
Version: 0.1.0
Author-email: Thomas Nicholas <tcnicholas@me.com>
License: MIT License
Project-URL: Homepage, https://github.com/tcnicholas/py-hrmc
Keywords: chemistry,total scattering,monte carlo
Classifier: License :: OSI Approved :: MIT License
Classifier: Programming Language :: Python
Classifier: Programming Language :: Python :: 3
Requires-Python: >=3.8
License-File: LICENSE
Requires-Dist: ase
Requires-Dist: numba
Requires-Dist: numpy
Requires-Dist: pylammpsmpi
